{
    "title": "你的第一本播客制作指南",
    "url": "https://xiaobot.net/p/podcast001?refer=f45527a5-d021-4bc8-958b-f28d2e90e7f7",
    "author_id": "podcast001",
    "author": "旺仔珂珂糖",
    "avatar": "https://static.xiaobot.net/paper/2022-12-17/30378/1c15182b170783938b3cc1706f6ec135.png",
    "reader_count": 3036,
    "article_count": 23,
    "intro": "hi，我是《末日狂花》、《消费圈内人》和前《温柔一刀》的制作人旺仔珂珂糖。\n我对本册子的定位是：最简单、最容易上手、不讲大道理，看完就能自己上手做的播客制作手册。\n\n- 限时258元（永久买断）\n- 满 3000 人涨价至 299 元\n\n\n付费之后，你将获得：\n- 20 篇播客制作步骤的详细拆解+播客创作者社群精华系列+主播锦囊系列，保姆级教程帮助你上手播客制作，少走弯路；\n- 独家播客创作者社群，可在群内认识其他的播客创作者伙伴；\n- 永久买断制，可以随时观看已发布的内容。",
    "commission_rate": 0.3,
    "last_update": "2024/01/02",
    "tags": [
        "内容制作",
        "内容定位",
        "运营推广",
        "加餐",
        "播客",
        "播客制作"
    ]
}